[
    {
        "ts_code":  "000001.SZ",
        "trade_date":  "20250630",
        "open":  12.14,
        "high":  12.17,
        "low":  11.96,
        "close":  12.07,
        "pre_close":  12.2,
        "change":  -0.13,
        "pct_chg":  -1.0656,
        "vol":  1504819.65,
        "amount":  1812492.377
    },
    {
        "ts_code":  "000001.SZ",
        "trade_date":  "20250701",
        "open":  12.06,
        "high":  12.33,
        "low":  12.06,
        "close":  12.3,
        "pre_close":  12.07,
        "change":  0.23,
        "pct_chg":  1.9056,
        "vol":  1354341.08,
        "amount":  1653806.75
    },
    {
        "ts_code":  "000001.SZ",
        "trade_date":  "20250702",
        "open":  12.31,
        "high":  12.41,
        "low":  12.23,
        "close":  12.32,
        "pre_close":  12.3,
        "change":  0.02,
        "pct_chg":  0.1626,
        "vol":  1200411.84,
        "amount":  1481842.213
    },
    {
        "ts_code":  "000001.SZ",
        "trade_date":  "20250703",
        "open":  12.33,
        "high":  12.42,
        "low":  12.28,
        "close":  12.35,
        "pre_close":  12.32,
        "change":  0.03,
        "pct_chg":  0.2435,
        "vol":  794085.97,
        "amount":  980546.007
    },
    {
        "ts_code":  "000001.SZ",
        "trade_date":  "20250704",
        "open":  12.35,
        "high":  12.72,
        "low":  12.3,
        "close":  12.6,
        "pre_close":  12.35,
        "change":  0.25,
        "pct_chg":  2.0243,
        "vol":  1775332.67,
        "amount":  2224874.056
    },
    {
        "ts_code":  "000001.SZ",
        "trade_date":  "20250707",
        "open":  12.6,
        "high":  12.82,
        "low":  12.6,
        "close":  12.78,
        "pre_close":  12.6,
        "change":  0.18,
        "pct_chg":  1.4286,
        "vol":  1495406.53,
        "amount":  1901755.851
    },
    {
        "ts_code":  "000001.SZ",
        "trade_date":  "20250708",
        "open":  12.75,
        "high":  12.84,
        "low":  12.65,
        "close":  12.69,
        "pre_close":  12.78,
        "change":  -0.09,
        "pct_chg":  -0.7042,
        "vol":  1090985.97,
        "amount":  1387093.602
    },
    {
        "ts_code":  "000001.SZ",
        "trade_date":  "20250709",
        "open":  12.66,
        "high":  12.9,
        "low":  12.66,
        "close":  12.84,
        "pre_close":  12.69,
        "change":  0.15,
        "pct_chg":  1.182,
        "vol":  1205963.3,
        "amount":  1542699.035
    },
    {
        "ts_code":  "000001.SZ",
        "trade_date":  "20250710",
        "open":  12.82,
        "high":  13.33,
        "low":  12.79,
        "close":  13.18,
        "pre_close":  12.84,
        "change":  0.34,
        "pct_chg":  2.648,
        "vol":  2481415.53,
        "amount":  3249454.029
    },
    {
        "ts_code":  "000001.SZ",
        "trade_date":  "20250711",
        "open":  13.19,
        "high":  13.3,
        "low":  12.89,
        "close":  12.91,
        "pre_close":  13.18,
        "change":  -0.27,
        "pct_chg":  -2.0486,
        "vol":  2443743.5,
        "amount":  3200219.566
    },
    {
        "ts_code":  "000001.SZ",
        "trade_date":  "20250714",
        "open":  12.87,
        "high":  13.17,
        "low":  12.86,
        "close":  12.98,
        "pre_close":  12.91,
        "change":  0.07,
        "pct_chg":  0.5422,
        "vol":  1872895.85,
        "amount":  2440924.105
    },
    {
        "ts_code":  "000001.SZ",
        "trade_date":  "20250715",
        "open":  12.99,
        "high":  13.04,
        "low":  12.71,
        "close":  12.73,
        "pre_close":  12.98,
        "change":  -0.25,
        "pct_chg":  -1.926,
        "vol":  1810531.31,
        "amount":  2322277.285
    },
    {
        "ts_code":  "000001.SZ",
        "trade_date":  "20250716",
        "open":  12.73,
        "high":  12.76,
        "low":  12.5,
        "close":  12.64,
        "pre_close":  12.73,
        "change":  -0.09,
        "pct_chg":  -0.707,
        "vol":  1927863.79,
        "amount":  2424983.973
    },
    {
        "ts_code":  "000001.SZ",
        "trade_date":  "20250717",
        "open":  12.61,
        "high":  12.7,
        "low":  12.54,
        "close":  12.59,
        "pre_close":  12.64,
        "change":  -0.05,
        "pct_chg":  -0.3956,
        "vol":  944641.4,
        "amount":  1189666.227
    },
    {
        "ts_code":  "000001.SZ",
        "trade_date":  "20250718",
        "open":  12.62,
        "high":  12.75,
        "low":  12.6,
        "close":  12.7,
        "pre_close":  12.59,
        "change":  0.11,
        "pct_chg":  0.8737,
        "vol":  1241206.11,
        "amount":  1574176.824
    },
    {
        "ts_code":  "000001.SZ",
        "trade_date":  "20250721",
        "open":  12.64,
        "high":  12.71,
        "low":  12.55,
        "close":  12.61,
        "pre_close":  12.7,
        "change":  -0.09,
        "pct_chg":  -0.7087,
        "vol":  1079026.62,
        "amount":  1360155.719
    },
    {
        "ts_code":  "000001.SZ",
        "trade_date":  "20250722",
        "open":  12.6,
        "high":  12.6,
        "low":  12.32,
        "close":  12.49,
        "pre_close":  12.61,
        "change":  -0.12,
        "pct_chg":  -0.9516,
        "vol":  1935229.16,
        "amount":  2408337.286
    },
    {
        "ts_code":  "000001.SZ",
        "trade_date":  "20250723",
        "open":  12.46,
        "high":  12.63,
        "low":  12.45,
        "close":  12.53,
        "pre_close":  12.49,
        "change":  0.04,
        "pct_chg":  0.3203,
        "vol":  1370520.0,
        "amount":  1719158.803
    },
    {
        "ts_code":  "000001.SZ",
        "trade_date":  "20250724",
        "open":  12.53,
        "high":  12.53,
        "low":  12.33,
        "close":  12.35,
        "pre_close":  12.53,
        "change":  -0.18,
        "pct_chg":  -1.4366,
        "vol":  1959350.57,
        "amount":  2426175.236
    },
    {
        "ts_code":  "000001.SZ",
        "trade_date":  "20250725",
        "open":  12.33,
        "high":  12.46,
        "low":  12.32,
        "close":  12.35,
        "pre_close":  12.35,
        "change":  0.0,
        "pct_chg":  0.0,
        "vol":  1108266.66,
        "amount":  1372103.731
    },
    {
        "ts_code":  "000001.SZ",
        "trade_date":  "20250728",
        "open":  12.35,
        "high":  12.53,
        "low":  12.32,
        "close":  12.46,
        "pre_close":  12.35,
        "change":  0.11,
        "pct_chg":  0.8907,
        "vol":  1238242.78,
        "amount":  1541317.047
    },
    {
        "ts_code":  "000001.SZ",
        "trade_date":  "20250729",
        "open":  12.46,
        "high":  12.51,
        "low":  12.34,
        "close":  12.34,
        "pre_close":  12.46,
        "change":  -0.12,
        "pct_chg":  -0.9631,
        "vol":  1012818.01,
        "amount":  1255113.972
    },
    {
        "ts_code":  "000001.SZ",
        "trade_date":  "20250730",
        "open":  12.35,
        "high":  12.64,
        "low":  12.34,
        "close":  12.49,
        "pre_close":  12.34,
        "change":  0.15,
        "pct_chg":  1.2156,
        "vol":  1715163.6,
        "amount":  2149934.405
    },
    {
        "ts_code":  "000001.SZ",
        "trade_date":  "20250731",
        "open":  12.51,
        "high":  12.55,
        "low":  12.22,
        "close":  12.23,
        "pre_close":  12.49,
        "change":  -0.26,
        "pct_chg":  -2.0817,
        "vol":  1690081.25,
        "amount":  2079630.602
    },
    {
        "ts_code":  "000001.SZ",
        "trade_date":  "20250801",
        "open":  12.24,
        "high":  12.33,
        "low":  12.15,
        "close":  12.28,
        "pre_close":  12.23,
        "change":  0.05,
        "pct_chg":  0.4088,
        "vol":  1012186.98,
        "amount":  1240239.18
    },
    {
        "ts_code":  "000001.SZ",
        "trade_date":  "20250804",
        "open":  12.24,
        "high":  12.38,
        "low":  12.21,
        "close":  12.3,
        "pre_close":  12.28,
        "change":  0.02,
        "pct_chg":  0.1629,
        "vol":  1032689.69,
        "amount":  1271376.407
    },
    {
        "ts_code":  "000001.SZ",
        "trade_date":  "20250805",
        "open":  12.3,
        "high":  12.5,
        "low":  12.28,
        "close":  12.47,
        "pre_close":  12.3,
        "change":  0.17,
        "pct_chg":  1.3821,
        "vol":  1132078.2,
        "amount":  1405152.349
    },
    {
        "ts_code":  "000001.SZ",
        "trade_date":  "20250806",
        "open":  12.47,
        "high":  12.52,
        "low":  12.4,
        "close":  12.46,
        "pre_close":  12.47,
        "change":  -0.01,
        "pct_chg":  -0.0802,
        "vol":  690447.65,
        "amount":  859684.675
    },
    {
        "ts_code":  "000001.SZ",
        "trade_date":  "20250807",
        "open":  12.44,
        "high":  12.53,
        "low":  12.39,
        "close":  12.47,
        "pre_close":  12.46,
        "change":  0.01,
        "pct_chg":  0.0803,
        "vol":  722053.05,
        "amount":  900760.013
    },
    {
        "ts_code":  "000001.SZ",
        "trade_date":  "20250808",
        "open":  12.48,
        "high":  12.53,
        "low":  12.39,
        "close":  12.4,
        "pre_close":  12.47,
        "change":  -0.07,
        "pct_chg":  -0.5613,
        "vol":  829795.91,
        "amount":  1032586.759
    },
    {
        "ts_code":  "000001.SZ",
        "trade_date":  "20250811",
        "open":  12.4,
        "high":  12.42,
        "low":  12.27,
        "close":  12.3,
        "pre_close":  12.4,
        "change":  -0.1,
        "pct_chg":  -0.8065,
        "vol":  934353.15,
        "amount":  1150305.113
    },
    {
        "ts_code":  "000001.SZ",
        "trade_date":  "20250812",
        "open":  12.3,
        "high":  12.4,
        "low":  12.3,
        "close":  12.33,
        "pre_close":  12.3,
        "change":  0.03,
        "pct_chg":  0.2439,
        "vol":  680056.19,
        "amount":  839635.63
    },
    {
        "ts_code":  "000001.SZ",
        "trade_date":  "20250813",
        "open":  12.37,
        "high":  12.4,
        "low":  12.23,
        "close":  12.26,
        "pre_close":  12.33,
        "change":  -0.07,
        "pct_chg":  -0.5677,
        "vol":  1119813.05,
        "amount":  1376777.909
    },
    {
        "ts_code":  "000001.SZ",
        "trade_date":  "20250814",
        "open":  12.27,
        "high":  12.34,
        "low":  12.19,
        "close":  12.2,
        "pre_close":  12.26,
        "change":  -0.06,
        "pct_chg":  -0.4894,
        "vol":  1241041.29,
        "amount":  1523447.932
    },
    {
        "ts_code":  "000001.SZ",
        "trade_date":  "20250815",
        "open":  12.23,
        "high":  12.23,
        "low":  11.94,
        "close":  12.08,
        "pre_close":  12.2,
        "change":  -0.12,
        "pct_chg":  -0.9836,
        "vol":  1948502.95,
        "amount":  2344073.499
    },
    {
        "ts_code":  "000001.SZ",
        "trade_date":  "20250818",
        "open":  12.06,
        "high":  12.15,
        "low":  12.03,
        "close":  12.08,
        "pre_close":  12.08,
        "change":  0.0,
        "pct_chg":  0.0,
        "vol":  1239058.37,
        "amount":  1496527.039
    },
    {
        "ts_code":  "000001.SZ",
        "trade_date":  "20250819",
        "open":  12.1,
        "high":  12.12,
        "low":  12.02,
        "close":  12.06,
        "pre_close":  12.08,
        "change":  -0.02,
        "pct_chg":  -0.1656,
        "vol":  892859.89,
        "amount":  1077380.173
    },
    {
        "ts_code":  "000001.SZ",
        "trade_date":  "20250820",
        "open":  12.06,
        "high":  12.12,
        "low":  11.98,
        "close":  12.07,
        "pre_close":  12.06,
        "change":  0.01,
        "pct_chg":  0.0829,
        "vol":  1048738.53,
        "amount":  1265435.773
    },
    {
        "ts_code":  "000001.SZ",
        "trade_date":  "20250821",
        "open":  12.05,
        "high":  12.19,
        "low":  12.03,
        "close":  12.15,
        "pre_close":  12.07,
        "change":  0.08,
        "pct_chg":  0.6628,
        "vol":  1217418.25,
        "amount":  1477053.292
    },
    {
        "ts_code":  "000001.SZ",
        "trade_date":  "20250822",
        "open":  12.15,
        "high":  12.17,
        "low":  11.98,
        "close":  12.06,
        "pre_close":  12.15,
        "change":  -0.09,
        "pct_chg":  -0.7407,
        "vol":  1644259.77,
        "amount":  1979461.311
    },
    {
        "ts_code":  "000001.SZ",
        "trade_date":  "20250825",
        "open":  12.12,
        "high":  12.53,
        "low":  12.1,
        "close":  12.45,
        "pre_close":  12.06,
        "change":  0.39,
        "pct_chg":  3.2338,
        "vol":  3045087.53,
        "amount":  3761289.076
    },
    {
        "ts_code":  "000001.SZ",
        "trade_date":  "20250826",
        "open":  12.45,
        "high":  12.5,
        "low":  12.3,
        "close":  12.36,
        "pre_close":  12.45,
        "change":  -0.09,
        "pct_chg":  -0.7229,
        "vol":  1383598.61,
        "amount":  1709560.923
    },
    {
        "ts_code":  "000001.SZ",
        "trade_date":  "20250827",
        "open":  12.32,
        "high":  12.36,
        "low":  12.05,
        "close":  12.06,
        "pre_close":  12.36,
        "change":  -0.3,
        "pct_chg":  -2.4272,
        "vol":  1860049.5,
        "amount":  2268070.721
    },
    {
        "ts_code":  "000001.SZ",
        "trade_date":  "20250828",
        "open":  12.09,
        "high":  12.14,
        "low":  11.97,
        "close":  12.08,
        "pre_close":  12.06,
        "change":  0.02,
        "pct_chg":  0.1658,
        "vol":  1653587.93,
        "amount":  1991723.374
    },
    {
        "ts_code":  "000001.SZ",
        "trade_date":  "20250829",
        "open":  12.05,
        "high":  12.22,
        "low":  12.03,
        "close":  12.05,
        "pre_close":  12.08,
        "change":  -0.03,
        "pct_chg":  -0.2483,
        "vol":  1805125.68,
        "amount":  2186232.853
    },
    {
        "ts_code":  "000001.SZ",
        "trade_date":  "20250901",
        "open":  12.05,
        "high":  12.05,
        "low":  11.85,
        "close":  11.89,
        "pre_close":  12.05,
        "change":  -0.16,
        "pct_chg":  -1.3278,
        "vol":  1858459.02,
        "amount":  2214306.332
    },
    {
        "ts_code":  "000001.SZ",
        "trade_date":  "20250902",
        "open":  11.85,
        "high":  11.99,
        "low":  11.84,
        "close":  11.98,
        "pre_close":  11.89,
        "change":  0.09,
        "pct_chg":  0.7569,
        "vol":  1492715.66,
        "amount":  1780010.209
    },
    {
        "ts_code":  "000001.SZ",
        "trade_date":  "20250903",
        "open":  11.98,
        "high":  12.01,
        "low":  11.74,
        "close":  11.75,
        "pre_close":  11.98,
        "change":  -0.23,
        "pct_chg":  -1.9199,
        "vol":  1367232.49,
        "amount":  1619322.977
    },
    {
        "ts_code":  "000001.SZ",
        "trade_date":  "20250904",
        "open":  11.76,
        "high":  11.77,
        "low":  11.6,
        "close":  11.74,
        "pre_close":  11.75,
        "change":  -0.01,
        "pct_chg":  -0.0851,
        "vol":  1295300.02,
        "amount":  1513956.779
    },
    {
        "ts_code":  "000001.SZ",
        "trade_date":  "20250905",
        "open":  11.73,
        "high":  11.74,
        "low":  11.63,
        "close":  11.72,
        "pre_close":  11.74,
        "change":  -0.02,
        "pct_chg":  -0.1704,
        "vol":  819661.56,
        "amount":  957547.463
    },
    {
        "ts_code":  "000001.SZ",
        "trade_date":  "20250908",
        "open":  11.71,
        "high":  11.78,
        "low":  11.67,
        "close":  11.7,
        "pre_close":  11.72,
        "change":  -0.02,
        "pct_chg":  -0.1706,
        "vol":  924431.04,
        "amount":  1083054.608
    },
    {
        "ts_code":  "000001.SZ",
        "trade_date":  "20250909",
        "open":  11.71,
        "high":  11.78,
        "low":  11.68,
        "close":  11.75,
        "pre_close":  11.7,
        "change":  0.05,
        "pct_chg":  0.4274,
        "vol":  860539.17,
        "amount":  1009279.729
    },
    {
        "ts_code":  "000001.SZ",
        "trade_date":  "20250910",
        "open":  11.74,
        "high":  11.79,
        "low":  11.71,
        "close":  11.77,
        "pre_close":  11.75,
        "change":  0.02,
        "pct_chg":  0.1702,
        "vol":  792668.39,
        "amount":  932170.201
    },
    {
        "ts_code":  "000001.SZ",
        "trade_date":  "20250911",
        "open":  11.77,
        "high":  11.85,
        "low":  11.71,
        "close":  11.85,
        "pre_close":  11.77,
        "change":  0.08,
        "pct_chg":  0.6797,
        "vol":  963931.63,
        "amount":  1134234.367
    },
    {
        "ts_code":  "000001.SZ",
        "trade_date":  "20250912",
        "open":  11.83,
        "high":  11.88,
        "low":  11.7,
        "close":  11.72,
        "pre_close":  11.85,
        "change":  -0.13,
        "pct_chg":  -1.097,
        "vol":  940385.1,
        "amount":  1107449.057
    },
    {
        "ts_code":  "000001.SZ",
        "trade_date":  "20250915",
        "open":  11.7,
        "high":  11.72,
        "low":  11.63,
        "close":  11.65,
        "pre_close":  11.72,
        "change":  -0.07,
        "pct_chg":  -0.5973,
        "vol":  840386.56,
        "amount":  980347.617
    },
    {
        "ts_code":  "000001.SZ",
        "trade_date":  "20250916",
        "open":  11.66,
        "high":  11.71,
        "low":  11.61,
        "close":  11.64,
        "pre_close":  11.65,
        "change":  -0.01,
        "pct_chg":  -0.0858,
        "vol":  708048.49,
        "amount":  825169.464
    },
    {
        "ts_code":  "000001.SZ",
        "trade_date":  "20250917",
        "open":  11.64,
        "high":  11.67,
        "low":  11.58,
        "close":  11.64,
        "pre_close":  11.64,
        "change":  0.0,
        "pct_chg":  0.0,
        "vol":  771128.93,
        "amount":  896750.27
    },
    {
        "ts_code":  "000001.SZ",
        "trade_date":  "20250918",
        "open":  11.65,
        "high":  11.66,
        "low":  11.38,
        "close":  11.41,
        "pre_close":  11.64,
        "change":  -0.23,
        "pct_chg":  -1.9759,
        "vol":  1386160.4,
        "amount":  1594827.2
    },
    {
        "ts_code":  "000001.SZ",
        "trade_date":  "20250919",
        "open":  11.41,
        "high":  11.51,
        "low":  11.37,
        "close":  11.45,
        "pre_close":  11.41,
        "change":  0.04,
        "pct_chg":  0.3506,
        "vol":  834651.23,
        "amount":  955004.097
    },
    {
        "ts_code":  "000001.SZ",
        "trade_date":  "20250922",
        "open":  11.44,
        "high":  11.47,
        "low":  11.37,
        "close":  11.38,
        "pre_close":  11.45,
        "change":  -0.07,
        "pct_chg":  -0.6114,
        "vol":  596402.32,
        "amount":  680158.439
    },
    {
        "ts_code":  "000001.SZ",
        "trade_date":  "20250923",
        "open":  11.37,
        "high":  11.58,
        "low":  11.32,
        "close":  11.52,
        "pre_close":  11.38,
        "change":  0.14,
        "pct_chg":  1.2302,
        "vol":  1341430.22,
        "amount":  1543271.185
    },
    {
        "ts_code":  "000001.SZ",
        "trade_date":  "20250924",
        "open":  11.51,
        "high":  11.62,
        "low":  11.43,
        "close":  11.46,
        "pre_close":  11.52,
        "change":  -0.06,
        "pct_chg":  -0.5208,
        "vol":  1139583.47,
        "amount":  1310214.181
    },
    {
        "ts_code":  "000001.SZ",
        "trade_date":  "20250925",
        "open":  11.43,
        "high":  11.47,
        "low":  11.36,
        "close":  11.4,
        "pre_close":  11.46,
        "change":  -0.06,
        "pct_chg":  -0.5236,
        "vol":  773275.94,
        "amount":  881943.148
    },
    {
        "ts_code":  "000001.SZ",
        "trade_date":  "20250926",
        "open":  11.39,
        "high":  11.44,
        "low":  11.32,
        "close":  11.4,
        "pre_close":  11.4,
        "change":  0.0,
        "pct_chg":  0.0,
        "vol":  753238.75,
        "amount":  856917.688
    },
    {
        "ts_code":  "000001.SZ",
        "trade_date":  "20250929",
        "open":  11.4,
        "high":  11.48,
        "low":  11.27,
        "close":  11.37,
        "pre_close":  11.4,
        "change":  -0.03,
        "pct_chg":  -0.2632,
        "vol":  1176012.43,
        "amount":  1334456.974
    },
    {
        "ts_code":  "000001.SZ",
        "trade_date":  "20250930",
        "open":  11.37,
        "high":  11.37,
        "low":  11.29,
        "close":  11.34,
        "pre_close":  11.37,
        "change":  -0.03,
        "pct_chg":  -0.2639,
        "vol":  832479.47,
        "amount":  942224.081
    },
    {
        "ts_code":  "000001.SZ",
        "trade_date":  "20251009",
        "open":  11.33,
        "high":  11.41,
        "low":  11.27,
        "close":  11.4,
        "pre_close":  11.34,
        "change":  0.06,
        "pct_chg":  0.5291,
        "vol":  1047469.06,
        "amount":  1187061.683
    },
    {
        "ts_code":  "000001.SZ",
        "trade_date":  "20251010",
        "open":  11.37,
        "high":  11.49,
        "low":  11.36,
        "close":  11.43,
        "pre_close":  11.4,
        "change":  0.03,
        "pct_chg":  0.2632,
        "vol":  1087947.75,
        "amount":  1244213.513
    },
    {
        "ts_code":  "000001.SZ",
        "trade_date":  "20251013",
        "open":  11.32,
        "high":  11.46,
        "low":  11.28,
        "close":  11.4,
        "pre_close":  11.43,
        "change":  -0.03,
        "pct_chg":  -0.2625,
        "vol":  1168801.73,
        "amount":  1328180.364
    },
    {
        "ts_code":  "000001.SZ",
        "trade_date":  "20251014",
        "open":  11.39,
        "high":  11.6,
        "low":  11.36,
        "close":  11.57,
        "pre_close":  11.4,
        "change":  0.17,
        "pct_chg":  1.4912,
        "vol":  1843428.36,
        "amount":  2124120.304
    },
    {
        "ts_code":  "000001.SZ",
        "trade_date":  "20251015",
        "open":  11.34,
        "high":  11.42,
        "low":  11.26,
        "close":  11.4,
        "pre_close":  11.33,
        "change":  0.07,
        "pct_chg":  0.6178,
        "vol":  1271061.03,
        "amount":  1443458.105
    },
    {
        "ts_code":  "000001.SZ",
        "trade_date":  "20251016",
        "open":  11.38,
        "high":  11.55,
        "low":  11.36,
        "close":  11.54,
        "pre_close":  11.4,
        "change":  0.14,
        "pct_chg":  1.2281,
        "vol":  1261936.87,
        "amount":  1447841.585
    },
    {
        "ts_code":  "000001.SZ",
        "trade_date":  "20251017",
        "open":  11.5,
        "high":  11.58,
        "low":  11.38,
        "close":  11.4,
        "pre_close":  11.54,
        "change":  -0.14,
        "pct_chg":  -1.2132,
        "vol":  1039666.32,
        "amount":  1193518.555
    },
    {
        "ts_code":  "000001.SZ",
        "trade_date":  "20251020",
        "open":  11.41,
        "high":  11.45,
        "low":  11.27,
        "close":  11.42,
        "pre_close":  11.4,
        "change":  0.02,
        "pct_chg":  0.1754,
        "vol":  952641.1,
        "amount":  1081829.7
    },
    {
        "ts_code":  "000001.SZ",
        "trade_date":  "20251021",
        "open":  11.4,
        "high":  11.47,
        "low":  11.39,
        "close":  11.43,
        "pre_close":  11.42,
        "change":  0.01,
        "pct_chg":  0.0876,
        "vol":  761164.62,
        "amount":  869658.08
    },
    {
        "ts_code":  "000001.SZ",
        "trade_date":  "20251022",
        "open":  11.4,
        "high":  11.54,
        "low":  11.4,
        "close":  11.52,
        "pre_close":  11.43,
        "change":  0.09,
        "pct_chg":  0.7874,
        "vol":  833703.19,
        "amount":  957661.636
    },
    {
        "ts_code":  "000001.SZ",
        "trade_date":  "20251023",
        "open":  11.52,
        "high":  11.71,
        "low":  11.5,
        "close":  11.63,
        "pre_close":  11.52,
        "change":  0.11,
        "pct_chg":  0.9549,
        "vol":  1373111.58,
        "amount":  1593155.218
    },
    {
        "ts_code":  "000001.SZ",
        "trade_date":  "20251024",
        "open":  11.6,
        "high":  11.68,
        "low":  11.55,
        "close":  11.56,
        "pre_close":  11.63,
        "change":  -0.07,
        "pct_chg":  -0.6019,
        "vol":  980475.3,
        "amount":  1138026.681
    },
    {
        "ts_code":  "000001.SZ",
        "trade_date":  "20251027",
        "open":  11.54,
        "high":  11.61,
        "low":  11.44,
        "close":  11.52,
        "pre_close":  11.56,
        "change":  -0.04,
        "pct_chg":  -0.346,
        "vol":  1239485.26,
        "amount":  1428199.707
    },
    {
        "ts_code":  "000001.SZ",
        "trade_date":  "20251028",
        "open":  11.53,
        "high":  11.58,
        "low":  11.42,
        "close":  11.47,
        "pre_close":  11.52,
        "change":  -0.05,
        "pct_chg":  -0.434,
        "vol":  821568.18,
        "amount":  943626.835
    },
    {
        "ts_code":  "000001.SZ",
        "trade_date":  "20251029",
        "open":  11.46,
        "high":  11.46,
        "low":  11.36,
        "close":  11.39,
        "pre_close":  11.47,
        "change":  -0.08,
        "pct_chg":  -0.6975,
        "vol":  966213.64,
        "amount":  1100783.363
    },
    {
        "ts_code":  "000001.SZ",
        "trade_date":  "20251030",
        "open":  11.38,
        "high":  11.47,
        "low":  11.36,
        "close":  11.38,
        "pre_close":  11.39,
        "change":  -0.01,
        "pct_chg":  -0.0878,
        "vol":  943770.15,
        "amount":  1077182.643
    },
    {
        "ts_code":  "000001.SZ",
        "trade_date":  "20251031",
        "open":  11.38,
        "high":  11.4,
        "low":  11.3,
        "close":  11.32,
        "pre_close":  11.38,
        "change":  -0.06,
        "pct_chg":  -0.5272,
        "vol":  970192.93,
        "amount":  1099179.193
    },
    {
        "ts_code":  "000001.SZ",
        "trade_date":  "20251103",
        "open":  11.34,
        "high":  11.44,
        "low":  11.3,
        "close":  11.43,
        "pre_close":  11.32,
        "change":  0.11,
        "pct_chg":  0.9717,
        "vol":  952326.43,
        "amount":  1084422.504
    },
    {
        "ts_code":  "000001.SZ",
        "trade_date":  "20251104",
        "open":  11.42,
        "high":  11.64,
        "low":  11.4,
        "close":  11.59,
        "pre_close":  11.43,
        "change":  0.16,
        "pct_chg":  1.3998,
        "vol":  1503007.48,
        "amount":  1737289.514
    },
    {
        "ts_code":  "000001.SZ",
        "trade_date":  "20251105",
        "open":  11.59,
        "high":  11.6,
        "low":  11.5,
        "close":  11.52,
        "pre_close":  11.59,
        "change":  -0.07,
        "pct_chg":  -0.604,
        "vol":  794926.05,
        "amount":  918112.474
    },
    {
        "ts_code":  "000001.SZ",
        "trade_date":  "20251106",
        "open":  11.5,
        "high":  11.58,
        "low":  11.47,
        "close":  11.51,
        "pre_close":  11.52,
        "change":  -0.01,
        "pct_chg":  -0.0868,
        "vol":  766585.46,
        "amount":  882799.462
    },
    {
        "ts_code":  "000001.SZ",
        "trade_date":  "20251107",
        "open":  11.52,
        "high":  11.58,
        "low":  11.5,
        "close":  11.55,
        "pre_close":  11.51,
        "change":  0.04,
        "pct_chg":  0.3475,
        "vol":  734850.55,
        "amount":  848177.984
    },
    {
        "ts_code":  "000001.SZ",
        "trade_date":  "20251110",
        "open":  11.52,
        "high":  11.64,
        "low":  11.45,
        "close":  11.63,
        "pre_close":  11.55,
        "change":  0.08,
        "pct_chg":  0.6926,
        "vol":  827208.33,
        "amount":  957555.601
    },
    {
        "ts_code":  "000001.SZ",
        "trade_date":  "20251111",
        "open":  11.62,
        "high":  11.69,
        "low":  11.57,
        "close":  11.67,
        "pre_close":  11.63,
        "change":  0.04,
        "pct_chg":  0.3439,
        "vol":  886508.87,
        "amount":  1033284.776
    },
    {
        "ts_code":  "000001.SZ",
        "trade_date":  "20251112",
        "open":  11.7,
        "high":  11.79,
        "low":  11.65,
        "close":  11.68,
        "pre_close":  11.67,
        "change":  0.01,
        "pct_chg":  0.0857,
        "vol":  1141325.38,
        "amount":  1337963.805
    },
    {
        "ts_code":  "000001.SZ",
        "trade_date":  "20251113",
        "open":  11.68,
        "high":  11.72,
        "low":  11.57,
        "close":  11.7,
        "pre_close":  11.68,
        "change":  0.02,
        "pct_chg":  0.1712,
        "vol":  978991.03,
        "amount":  1139765.204
    },
    {
        "ts_code":  "000001.SZ",
        "trade_date":  "20251114",
        "open":  11.67,
        "high":  11.84,
        "low":  11.66,
        "close":  11.75,
        "pre_close":  11.7,
        "change":  0.05,
        "pct_chg":  0.4274,
        "vol":  1316994.98,
        "amount":  1551867.288
    },
    {
        "ts_code":  "000001.SZ",
        "trade_date":  "20251117",
        "open":  11.75,
        "high":  11.75,
        "low":  11.62,
        "close":  11.67,
        "pre_close":  11.75,
        "change":  -0.08,
        "pct_chg":  -0.6809,
        "vol":  995232.87,
        "amount":  1161416.222
    },
    {
        "ts_code":  "000001.SZ",
        "trade_date":  "20251118",
        "open":  11.65,
        "high":  11.69,
        "low":  11.57,
        "close":  11.59,
        "pre_close":  11.67,
        "change":  -0.08,
        "pct_chg":  -0.6855,
        "vol":  670077.35,
        "amount":  778887.578
    },
    {
        "ts_code":  "000001.SZ",
        "trade_date":  "20251119",
        "open":  11.58,
        "high":  11.83,
        "low":  11.57,
        "close":  11.8,
        "pre_close":  11.59,
        "change":  0.21,
        "pct_chg":  1.8119,
        "vol":  1334996.19,
        "amount":  1565428.547
    },
    {
        "ts_code":  "000001.SZ",
        "trade_date":  "20251120",
        "open":  11.79,
        "high":  11.99,
        "low":  11.74,
        "close":  11.85,
        "pre_close":  11.8,
        "change":  0.05,
        "pct_chg":  0.4237,
        "vol":  1637039.85,
        "amount":  1948415.94
    },
    {
        "ts_code":  "000001.SZ",
        "trade_date":  "20251121",
        "open":  11.8,
        "high":  11.88,
        "low":  11.66,
        "close":  11.69,
        "pre_close":  11.85,
        "change":  -0.16,
        "pct_chg":  -1.3502,
        "vol":  1465358.88,
        "amount":  1721871.193
    },
    {
        "ts_code":  "000001.SZ",
        "trade_date":  "20251124",
        "open":  11.7,
        "high":  11.73,
        "low":  11.6,
        "close":  11.6,
        "pre_close":  11.69,
        "change":  -0.09,
        "pct_chg":  -0.7699,
        "vol":  1117118.8,
        "amount":  1302444.63
    },
    {
        "ts_code":  "000001.SZ",
        "trade_date":  "20251125",
        "open":  11.61,
        "high":  11.8,
        "low":  11.58,
        "close":  11.8,
        "pre_close":  11.6,
        "change":  0.2,
        "pct_chg":  1.7241,
        "vol":  1028080.52,
        "amount":  1203879.797
    },
    {
        "ts_code":  "000001.SZ",
        "trade_date":  "20251126",
        "open":  11.81,
        "high":  11.85,
        "low":  11.65,
        "close":  11.69,
        "pre_close":  11.8,
        "change":  -0.11,
        "pct_chg":  -0.9322,
        "vol":  821301.09,
        "amount":  962935.43
    },
    {
        "ts_code":  "000001.SZ",
        "trade_date":  "20251127",
        "open":  11.66,
        "high":  11.71,
        "low":  11.58,
        "close":  11.71,
        "pre_close":  11.69,
        "change":  0.02,
        "pct_chg":  0.1711,
        "vol":  1011847.1,
        "amount":  1178308.953
    },
    {
        "ts_code":  "000001.SZ",
        "trade_date":  "20251128",
        "open":  11.67,
        "high":  11.68,
        "low":  11.58,
        "close":  11.61,
        "pre_close":  11.71,
        "change":  -0.1,
        "pct_chg":  -0.854,
        "vol":  884358.45,
        "amount":  1027933.464
    },
    {
        "ts_code":  "000001.SZ",
        "trade_date":  "20251201",
        "open":  11.6,
        "high":  11.7,
        "low":  11.53,
        "close":  11.69,
        "pre_close":  11.61,
        "change":  0.08,
        "pct_chg":  0.6891,
        "vol":  1037322.71,
        "amount":  1205480.323
    },
    {
        "ts_code":  "000001.SZ",
        "trade_date":  "20251202",
        "open":  11.68,
        "high":  11.73,
        "low":  11.59,
        "close":  11.64,
        "pre_close":  11.69,
        "change":  -0.05,
        "pct_chg":  -0.4277,
        "vol":  768059.93,
        "amount":  894720.592
    },
    {
        "ts_code":  "000001.SZ",
        "trade_date":  "20251203",
        "open":  11.64,
        "high":  11.7,
        "low":  11.54,
        "close":  11.55,
        "pre_close":  11.64,
        "change":  -0.09,
        "pct_chg":  -0.7732,
        "vol":  944601.09,
        "amount":  1099167.227
    },
    {
        "ts_code":  "000001.SZ",
        "trade_date":  "20251204",
        "open":  11.55,
        "high":  11.58,
        "low":  11.46,
        "close":  11.49,
        "pre_close":  11.55,
        "change":  -0.06,
        "pct_chg":  -0.5195,
        "vol":  886089.88,
        "amount":  1019178.99
    },
    {
        "ts_code":  "000001.SZ",
        "trade_date":  "20251205",
        "open":  11.49,
        "high":  11.54,
        "low":  11.4,
        "close":  11.53,
        "pre_close":  11.49,
        "change":  0.04,
        "pct_chg":  0.3481,
        "vol":  890766.09,
        "amount":  1022334.912
    },
    {
        "ts_code":  "000001.SZ",
        "trade_date":  "20251208",
        "open":  11.49,
        "high":  11.6,
        "low":  11.48,
        "close":  11.52,
        "pre_close":  11.53,
        "change":  -0.01,
        "pct_chg":  -0.0867,
        "vol":  855898.93,
        "amount":  988510.035
    },
    {
        "ts_code":  "000001.SZ",
        "trade_date":  "20251209",
        "open":  11.52,
        "high":  11.54,
        "low":  11.43,
        "close":  11.43,
        "pre_close":  11.52,
        "change":  -0.09,
        "pct_chg":  -0.7813,
        "vol":  733957.45,
        "amount":  842732.358
    },
    {
        "ts_code":  "000001.SZ",
        "trade_date":  "20251210",
        "open":  11.44,
        "high":  11.46,
        "low":  11.29,
        "close":  11.33,
        "pre_close":  11.43,
        "change":  -0.1,
        "pct_chg":  -0.8749,
        "vol":  1044064.72,
        "amount":  1184087.688
    },
    {
        "ts_code":  "000001.SZ",
        "trade_date":  "20251211",
        "open":  11.35,
        "high":  11.39,
        "low":  11.3,
        "close":  11.37,
        "pre_close":  11.33,
        "change":  0.04,
        "pct_chg":  0.353,
        "vol":  925261.29,
        "amount":  1049906.216
    },
    {
        "ts_code":  "000001.SZ",
        "trade_date":  "20251212",
        "open":  11.37,
        "high":  11.43,
        "low":  11.3,
        "close":  11.35,
        "pre_close":  11.37,
        "change":  -0.02,
        "pct_chg":  -0.1759,
        "vol":  1191894.72,
        "amount":  1357465.371
    },
    {
        "ts_code":  "000001.SZ",
        "trade_date":  "20251215",
        "open":  11.34,
        "high":  11.54,
        "low":  11.33,
        "close":  11.51,
        "pre_close":  11.35,
        "change":  0.16,
        "pct_chg":  1.4097,
        "vol":  940832.53,
        "amount":  1080642.231
    },
    {
        "ts_code":  "000001.SZ",
        "trade_date":  "20251216",
        "open":  11.49,
        "high":  11.55,
        "low":  11.44,
        "close":  11.48,
        "pre_close":  11.51,
        "change":  -0.03,
        "pct_chg":  -0.2606,
        "vol":  647351.36,
        "amount":  743389.002
    },
    {
        "ts_code":  "000001.SZ",
        "trade_date":  "20251217",
        "open":  11.47,
        "high":  11.58,
        "low":  11.42,
        "close":  11.53,
        "pre_close":  11.48,
        "change":  0.05,
        "pct_chg":  0.4355,
        "vol":  701495.33,
        "amount":  807135.164
    },
    {
        "ts_code":  "000001.SZ",
        "trade_date":  "20251218",
        "open":  11.51,
        "high":  11.65,
        "low":  11.48,
        "close":  11.64,
        "pre_close":  11.53,
        "change":  0.11,
        "pct_chg":  0.954,
        "vol":  790466.54,
        "amount":  916247.611
    },
    {
        "ts_code":  "000001.SZ",
        "trade_date":  "20251219",
        "open":  11.63,
        "high":  11.65,
        "low":  11.58,
        "close":  11.62,
        "pre_close":  11.64,
        "change":  -0.02,
        "pct_chg":  -0.1718,
        "vol":  649886.19,
        "amount":  755106.127
    },
    {
        "ts_code":  "000001.SZ",
        "trade_date":  "20251222",
        "open":  11.61,
        "high":  11.61,
        "low":  11.51,
        "close":  11.52,
        "pre_close":  11.62,
        "change":  -0.1,
        "pct_chg":  -0.8606,
        "vol":  742369.16,
        "amount":  857197.057
    },
    {
        "ts_code":  "000001.SZ",
        "trade_date":  "20251223",
        "open":  11.52,
        "high":  11.6,
        "low":  11.5,
        "close":  11.56,
        "pre_close":  11.52,
        "change":  0.04,
        "pct_chg":  0.3472,
        "vol":  666265.74,
        "amount":  770081.94
    },
    {
        "ts_code":  "000001.SZ",
        "trade_date":  "20251224",
        "open":  11.55,
        "high":  11.58,
        "low":  11.49,
        "close":  11.54,
        "pre_close":  11.56,
        "change":  -0.02,
        "pct_chg":  -0.173,
        "vol":  505243.56,
        "amount":  582458.735
    },
    {
        "ts_code":  "000001.SZ",
        "trade_date":  "20251225",
        "open":  11.54,
        "high":  11.62,
        "low":  11.52,
        "close":  11.56,
        "pre_close":  11.54,
        "change":  0.02,
        "pct_chg":  0.1733,
        "vol":  547455.23,
        "amount":  633772.625
    },
    {
        "ts_code":  "000001.SZ",
        "trade_date":  "20251226",
        "open":  11.56,
        "high":  11.59,
        "low":  11.53,
        "close":  11.54,
        "pre_close":  11.56,
        "change":  -0.02,
        "pct_chg":  -0.173,
        "vol":  436339.84,
        "amount":  504079.28
    },
    {
        "ts_code":  "000001.SZ",
        "trade_date":  "20251229",
        "open":  11.54,
        "high":  11.62,
        "low":  11.5,
        "close":  11.56,
        "pre_close":  11.54,
        "change":  0.02,
        "pct_chg":  0.1733,
        "vol":  648295.42,
        "amount":  749082.978
    },
    {
        "ts_code":  "000001.SZ",
        "trade_date":  "20251230",
        "open":  11.53,
        "high":  11.56,
        "low":  11.45,
        "close":  11.48,
        "pre_close":  11.56,
        "change":  -0.08,
        "pct_chg":  -0.692,
        "vol":  582584.33,
        "amount":  669409.275
    },
    {
        "ts_code":  "000001.SZ",
        "trade_date":  "20251231",
        "open":  11.48,
        "high":  11.49,
        "low":  11.4,
        "close":  11.41,
        "pre_close":  11.48,
        "change":  -0.07,
        "pct_chg":  -0.6098,
        "vol":  590620.37,
        "amount":  675457.357
    },
    {
        "ts_code":  "000001.SZ",
        "trade_date":  "20260105",
        "open":  11.42,
        "high":  11.51,
        "low":  11.41,
        "close":  11.5,
        "pre_close":  11.41,
        "change":  0.09,
        "pct_chg":  0.7888,
        "vol":  875491.18,
        "amount":  1003479.224
    },
    {
        "ts_code":  "000001.SZ",
        "trade_date":  "20260106",
        "open":  11.5,
        "high":  11.68,
        "low":  11.48,
        "close":  11.67,
        "pre_close":  11.5,
        "change":  0.17,
        "pct_chg":  1.4783,
        "vol":  1304648.42,
        "amount":  1512911.584
    },
    {
        "ts_code":  "000001.SZ",
        "trade_date":  "20260107",
        "open":  11.66,
        "high":  11.82,
        "low":  11.62,
        "close":  11.64,
        "pre_close":  11.67,
        "change":  -0.03,
        "pct_chg":  -0.2571,
        "vol":  966236.24,
        "amount":  1131165.699
    },
    {
        "ts_code":  "000001.SZ",
        "trade_date":  "20260108",
        "open":  11.64,
        "high":  11.65,
        "low":  11.49,
        "close":  11.51,
        "pre_close":  11.64,
        "change":  -0.13,
        "pct_chg":  -1.1168,
        "vol":  1100085.11,
        "amount":  1268647.295
    },
    {
        "ts_code":  "000001.SZ",
        "trade_date":  "20260109",
        "open":  11.53,
        "high":  11.53,
        "low":  11.44,
        "close":  11.46,
        "pre_close":  11.51,
        "change":  -0.05,
        "pct_chg":  -0.4344,
        "vol":  983390.04,
        "amount":  1128076.547
    },
    {
        "ts_code":  "000001.SZ",
        "trade_date":  "20260112",
        "open":  11.45,
        "high":  11.49,
        "low":  11.42,
        "close":  11.48,
        "pre_close":  11.46,
        "change":  0.02,
        "pct_chg":  0.1745,
        "vol":  855212.98,
        "amount":  979700.148
    },
    {
        "ts_code":  "000001.SZ",
        "trade_date":  "20260113",
        "open":  11.48,
        "high":  11.54,
        "low":  11.44,
        "close":  11.47,
        "pre_close":  11.48,
        "change":  -0.01,
        "pct_chg":  -0.0871,
        "vol":  1061541.22,
        "amount":  1219755.569
    },
    {
        "ts_code":  "000001.SZ",
        "trade_date":  "20260114",
        "open":  11.47,
        "high":  11.47,
        "low":  11.35,
        "close":  11.36,
        "pre_close":  11.47,
        "change":  -0.11,
        "pct_chg":  -0.959,
        "vol":  1274757.14,
        "amount":  1454416.591
    },
    {
        "ts_code":  "000001.SZ",
        "trade_date":  "20260115",
        "open":  11.33,
        "high":  11.37,
        "low":  11.3,
        "close":  11.31,
        "pre_close":  11.36,
        "change":  -0.05,
        "pct_chg":  -0.4401,
        "vol":  884959.77,
        "amount":  1002514.947
    },
    {
        "ts_code":  "000001.SZ",
        "trade_date":  "20260116",
        "open":  11.34,
        "high":  11.34,
        "low":  11.16,
        "close":  11.19,
        "pre_close":  11.31,
        "change":  -0.12,
        "pct_chg":  -1.061,
        "vol":  1119472.54,
        "amount":  1257713.579
    },
    {
        "ts_code":  "000001.SZ",
        "trade_date":  "20260119",
        "open":  11.15,
        "high":  11.21,
        "low":  11.11,
        "close":  11.12,
        "pre_close":  11.19,
        "change":  -0.07,
        "pct_chg":  -0.6256,
        "vol":  804741.31,
        "amount":  896712.443
    },
    {
        "ts_code":  "000001.SZ",
        "trade_date":  "20260120",
        "open":  11.12,
        "high":  11.2,
        "low":  11.11,
        "close":  11.16,
        "pre_close":  11.12,
        "change":  0.04,
        "pct_chg":  0.3597,
        "vol":  772276.09,
        "amount":  861694.178
    },
    {
        "ts_code":  "000001.SZ",
        "trade_date":  "20260121",
        "open":  11.15,
        "high":  11.18,
        "low":  11.06,
        "close":  11.07,
        "pre_close":  11.16,
        "change":  -0.09,
        "pct_chg":  -0.8065,
        "vol":  900124.91,
        "amount":  1001045.288
    },
    {
        "ts_code":  "000001.SZ",
        "trade_date":  "20260122",
        "open":  11.07,
        "high":  11.15,
        "low":  11.05,
        "close":  11.07,
        "pre_close":  11.07,
        "change":  0.0,
        "pct_chg":  0.0,
        "vol":  788634.62,
        "amount":  873985.785
    },
    {
        "ts_code":  "000001.SZ",
        "trade_date":  "20260123",
        "open":  11.07,
        "high":  11.09,
        "low":  10.98,
        "close":  10.99,
        "pre_close":  11.07,
        "change":  -0.08,
        "pct_chg":  -0.7227,
        "vol":  1109994.29,
        "amount":  1224886.436
    },
    {
        "ts_code":  "000001.SZ",
        "trade_date":  "20260126",
        "open":  10.98,
        "high":  11.06,
        "low":  10.92,
        "close":  10.96,
        "pre_close":  10.99,
        "change":  -0.03,
        "pct_chg":  -0.273,
        "vol":  1106246.65,
        "amount":  1214803.431
    },
    {
        "ts_code":  "000001.SZ",
        "trade_date":  "20260127",
        "open":  10.96,
        "high":  11.03,
        "low":  10.93,
        "close":  10.94,
        "pre_close":  10.96,
        "change":  -0.02,
        "pct_chg":  -0.1825,
        "vol":  894091.21,
        "amount":  981119.838
    },
    {
        "ts_code":  "000001.SZ",
        "trade_date":  "20260128",
        "open":  10.94,
        "high":  10.99,
        "low":  10.82,
        "close":  10.84,
        "pre_close":  10.94,
        "change":  -0.1,
        "pct_chg":  -0.9141,
        "vol":  1438766.03,
        "amount":  1570012.85
    },
    {
        "ts_code":  "000001.SZ",
        "trade_date":  "20260129",
        "open":  10.84,
        "high":  10.98,
        "low":  10.66,
        "close":  10.96,
        "pre_close":  10.84,
        "change":  0.12,
        "pct_chg":  1.107,
        "vol":  1852993.83,
        "amount":  2001845.208
    },
    {
        "ts_code":  "000001.SZ",
        "trade_date":  "20260130",
        "open":  10.94,
        "high":  11.03,
        "low":  10.83,
        "close":  10.83,
        "pre_close":  10.96,
        "change":  -0.13,
        "pct_chg":  -1.1861,
        "vol":  1091754.97,
        "amount":  1191181.198
    },
    {
        "ts_code":  "000001.SZ",
        "trade_date":  "20260202",
        "open":  10.82,
        "high":  11.03,
        "low":  10.8,
        "close":  10.86,
        "pre_close":  10.83,
        "change":  0.03,
        "pct_chg":  0.277,
        "vol":  1223173.02,
        "amount":  1337643.445
    },
    {
        "ts_code":  "000001.SZ",
        "trade_date":  "20260203",
        "open":  10.89,
        "high":  10.9,
        "low":  10.77,
        "close":  10.84,
        "pre_close":  10.86,
        "change":  -0.02,
        "pct_chg":  -0.1842,
        "vol":  806628.16,
        "amount":  872562.155
    },
    {
        "ts_code":  "000001.SZ",
        "trade_date":  "20260204",
        "open":  10.85,
        "high":  10.98,
        "low":  10.84,
        "close":  10.97,
        "pre_close":  10.84,
        "change":  0.13,
        "pct_chg":  1.1993,
        "vol":  695415.47,
        "amount":  760107.689
    },
    {
        "ts_code":  "000001.SZ",
        "trade_date":  "20260205",
        "open":  10.98,
        "high":  11.11,
        "low":  10.96,
        "close":  11.09,
        "pre_close":  10.97,
        "change":  0.12,
        "pct_chg":  1.0939,
        "vol":  1177591.09,
        "amount":  1301134.142
    },
    {
        "ts_code":  "000001.SZ",
        "trade_date":  "20260206",
        "open":  11.08,
        "high":  11.14,
        "low":  10.99,
        "close":  11.05,
        "pre_close":  11.09,
        "change":  -0.04,
        "pct_chg":  -0.3607,
        "vol":  727709.59,
        "amount":  803862.241
    },
    {
        "ts_code":  "000001.SZ",
        "trade_date":  "20260209",
        "open":  11.05,
        "high":  11.11,
        "low":  11.01,
        "close":  11.07,
        "pre_close":  11.05,
        "change":  0.02,
        "pct_chg":  0.181,
        "vol":  619716.7,
        "amount":  685218.215
    },
    {
        "ts_code":  "000001.SZ",
        "trade_date":  "20260210",
        "open":  11.07,
        "high":  11.1,
        "low":  11.02,
        "close":  11.06,
        "pre_close":  11.07,
        "change":  -0.01,
        "pct_chg":  -0.0903,
        "vol":  600429.99,
        "amount":  664140.162
    },
    {
        "ts_code":  "000001.SZ",
        "trade_date":  "20260211",
        "open":  11.06,
        "high":  11.09,
        "low":  11.02,
        "close":  11.07,
        "pre_close":  11.06,
        "change":  0.01,
        "pct_chg":  0.0904,
        "vol":  431040.98,
        "amount":  476801.864
    },
    {
        "ts_code":  "000001.SZ",
        "trade_date":  "20260212",
        "open":  11.07,
        "high":  11.08,
        "low":  10.93,
        "close":  10.96,
        "pre_close":  11.07,
        "change":  -0.11,
        "pct_chg":  -0.9937,
        "vol":  681340.24,
        "amount":  748338.547
    },
    {
        "ts_code":  "000001.SZ",
        "trade_date":  "20260213",
        "open":  10.96,
        "high":  10.99,
        "low":  10.9,
        "close":  10.91,
        "pre_close":  10.96,
        "change":  -0.05,
        "pct_chg":  -0.4562,
        "vol":  555047.36,
        "amount":  607501.376
    },
    {
        "ts_code":  "000001.SZ",
        "trade_date":  "20260224",
        "open":  10.93,
        "high":  10.95,
        "low":  10.88,
        "close":  10.91,
        "pre_close":  10.91,
        "change":  0.0,
        "pct_chg":  0.0,
        "vol":  602512.4,
        "amount":  657487.7
    },
    {
        "ts_code":  "000001.SZ",
        "trade_date":  "20260225",
        "open":  10.91,
        "high":  10.95,
        "low":  10.78,
        "close":  10.86,
        "pre_close":  10.91,
        "change":  -0.05,
        "pct_chg":  -0.4583,
        "vol":  1063134.87,
        "amount":  1156693.737
    },
    {
        "ts_code":  "000001.SZ",
        "trade_date":  "20260226",
        "open":  10.86,
        "high":  10.91,
        "low":  10.8,
        "close":  10.87,
        "pre_close":  10.86,
        "change":  0.01,
        "pct_chg":  0.0921,
        "vol":  712730.19,
        "amount":  772947.727
    },
    {
        "ts_code":  "000001.SZ",
        "trade_date":  "20260227",
        "open":  10.86,
        "high":  10.92,
        "low":  10.84,
        "close":  10.9,
        "pre_close":  10.87,
        "change":  0.03,
        "pct_chg":  0.276,
        "vol":  612227.96,
        "amount":  666177.346
    },
    {
        "ts_code":  "000001.SZ",
        "trade_date":  "20260302",
        "open":  10.85,
        "high":  10.89,
        "low":  10.77,
        "close":  10.85,
        "pre_close":  10.9,
        "change":  -0.05,
        "pct_chg":  -0.4587,
        "vol":  838873.55,
        "amount":  908747.812
    },
    {
        "ts_code":  "000001.SZ",
        "trade_date":  "20260303",
        "open":  10.85,
        "high":  10.95,
        "low":  10.8,
        "close":  10.88,
        "pre_close":  10.85,
        "change":  0.03,
        "pct_chg":  0.2765,
        "vol":  1028694.83,
        "amount":  1119402.076
    },
    {
        "ts_code":  "000001.SZ",
        "trade_date":  "20260304",
        "open":  10.84,
        "high":  10.84,
        "low":  10.67,
        "close":  10.71,
        "pre_close":  10.88,
        "change":  -0.17,
        "pct_chg":  -1.5625,
        "vol":  1089713.96,
        "amount":  1167995.856
    },
    {
        "ts_code":  "000001.SZ",
        "trade_date":  "20260305",
        "open":  10.72,
        "high":  10.84,
        "low":  10.7,
        "close":  10.81,
        "pre_close":  10.71,
        "change":  0.1,
        "pct_chg":  0.9337,
        "vol":  712641.18,
        "amount":  768553.598
    },
    {
        "ts_code":  "000001.SZ",
        "trade_date":  "20260306",
        "open":  10.78,
        "high":  10.84,
        "low":  10.77,
        "close":  10.82,
        "pre_close":  10.81,
        "change":  0.01,
        "pct_chg":  0.0925,
        "vol":  476576.8,
        "amount":  514733.55
    },
    {
        "ts_code":  "000001.SZ",
        "trade_date":  "20260309",
        "open":  10.79,
        "high":  10.82,
        "low":  10.74,
        "close":  10.76,
        "pre_close":  10.82,
        "change":  -0.06,
        "pct_chg":  -0.5545,
        "vol":  835892.38,
        "amount":  900716.851
    },
    {
        "ts_code":  "000001.SZ",
        "trade_date":  "20260310",
        "open":  10.77,
        "high":  10.81,
        "low":  10.73,
        "close":  10.81,
        "pre_close":  10.76,
        "change":  0.05,
        "pct_chg":  0.4647,
        "vol":  790111.68,
        "amount":  850573.536
    },
    {
        "ts_code":  "000001.SZ",
        "trade_date":  "20260311",
        "open":  10.79,
        "high":  10.9,
        "low":  10.77,
        "close":  10.89,
        "pre_close":  10.81,
        "change":  0.08,
        "pct_chg":  0.7401,
        "vol":  720534.64,
        "amount":  781041.009
    },
    {
        "ts_code":  "000001.SZ",
        "trade_date":  "20260312",
        "open":  10.87,
        "high":  10.96,
        "low":  10.85,
        "close":  10.94,
        "pre_close":  10.89,
        "change":  0.05,
        "pct_chg":  0.4591,
        "vol":  754905.58,
        "amount":  824171.954
    },
    {
        "ts_code":  "000001.SZ",
        "trade_date":  "20260313",
        "open":  10.93,
        "high":  11.0,
        "low":  10.87,
        "close":  10.93,
        "pre_close":  10.94,
        "change":  -0.01,
        "pct_chg":  -0.0914,
        "vol":  841939.15,
        "amount":  920839.356
    },
    {
        "ts_code":  "000001.SZ",
        "trade_date":  "20260316",
        "open":  10.93,
        "high":  10.97,
        "low":  10.88,
        "close":  10.92,
        "pre_close":  10.93,
        "change":  -0.01,
        "pct_chg":  -0.0915,
        "vol":  715603.01,
        "amount":  782089.441
    },
    {
        "ts_code":  "000001.SZ",
        "trade_date":  "20260317",
        "open":  10.91,
        "high":  11.07,
        "low":  10.9,
        "close":  11.03,
        "pre_close":  10.92,
        "change":  0.11,
        "pct_chg":  1.0073,
        "vol":  1076656.81,
        "amount":  1187565.492
    },
    {
        "ts_code":  "000001.SZ",
        "trade_date":  "20260318",
        "open":  11.04,
        "high":  11.04,
        "low":  10.91,
        "close":  10.96,
        "pre_close":  11.03,
        "change":  -0.07,
        "pct_chg":  -0.6346,
        "vol":  791079.4,
        "amount":  867711.25
    },
    {
        "ts_code":  "000001.SZ",
        "trade_date":  "20260319",
        "open":  10.92,
        "high":  10.97,
        "low":  10.86,
        "close":  10.88,
        "pre_close":  10.96,
        "change":  -0.08,
        "pct_chg":  -0.7299,
        "vol":  624211.95,
        "amount":  681086.519
    },
    {
        "ts_code":  "000001.SZ",
        "trade_date":  "20260320",
        "open":  10.87,
        "high":  10.94,
        "low":  10.76,
        "close":  10.77,
        "pre_close":  10.88,
        "change":  -0.11,
        "pct_chg":  -1.011,
        "vol":  834082.56,
        "amount":  903819.004
    },
    {
        "ts_code":  "000001.SZ",
        "trade_date":  "20260323",
        "open":  10.68,
        "high":  10.68,
        "low":  10.43,
        "close":  10.45,
        "pre_close":  10.77,
        "change":  -0.32,
        "pct_chg":  -2.9712,
        "vol":  1580088.33,
        "amount":  1666328.348
    },
    {
        "ts_code":  "000001.SZ",
        "trade_date":  "20260324",
        "open":  10.52,
        "high":  10.89,
        "low":  10.52,
        "close":  10.88,
        "pre_close":  10.45,
        "change":  0.43,
        "pct_chg":  4.1148,
        "vol":  1622251.27,
        "amount":  1744746.708
    },
    {
        "ts_code":  "000001.SZ",
        "trade_date":  "20260325",
        "open":  10.89,
        "high":  10.95,
        "low":  10.79,
        "close":  10.94,
        "pre_close":  10.88,
        "change":  0.06,
        "pct_chg":  0.5515,
        "vol":  744779.91,
        "amount":  809739.89
    },
    {
        "ts_code":  "000001.SZ",
        "trade_date":  "20260326",
        "open":  10.91,
        "high":  11.05,
        "low":  10.9,
        "close":  10.94,
        "pre_close":  10.94,
        "change":  0.0,
        "pct_chg":  0.0,
        "vol":  827664.09,
        "amount":  909199.431
    },
    {
        "ts_code":  "000001.SZ",
        "trade_date":  "20260327",
        "open":  10.91,
        "high":  11.05,
        "low":  10.83,
        "close":  11.02,
        "pre_close":  10.94,
        "change":  0.08,
        "pct_chg":  0.7313,
        "vol":  884128.62,
        "amount":  972821.27
    },
    {
        "ts_code":  "000001.SZ",
        "trade_date":  "20260330",
        "open":  10.98,
        "high":  11.05,
        "low":  10.94,
        "close":  10.99,
        "pre_close":  11.02,
        "change":  -0.03,
        "pct_chg":  -0.2722,
        "vol":  632522.1,
        "amount":  696208.267
    },
    {
        "ts_code":  "000001.SZ",
        "trade_date":  "20260331",
        "open":  11.0,
        "high":  11.18,
        "low":  10.99,
        "close":  11.08,
        "pre_close":  10.99,
        "change":  0.09,
        "pct_chg":  0.8189,
        "vol":  1164565.34,
        "amount":  1294675.716
    },
    {
        "ts_code":  "000001.SZ",
        "trade_date":  "20260401",
        "open":  11.09,
        "high":  11.23,
        "low":  11.08,
        "close":  11.15,
        "pre_close":  11.08,
        "change":  0.07,
        "pct_chg":  0.6318,
        "vol":  918925.39,
        "amount":  1025538.833
    },
    {
        "ts_code":  "000001.SZ",
        "trade_date":  "20260402",
        "open":  11.15,
        "high":  11.32,
        "low":  11.13,
        "close":  11.27,
        "pre_close":  11.15,
        "change":  0.12,
        "pct_chg":  1.0762,
        "vol":  1148895.22,
        "amount":  1292756.712
    },
    {
        "ts_code":  "000001.SZ",
        "trade_date":  "20260403",
        "open":  11.28,
        "high":  11.28,
        "low":  11.09,
        "close":  11.12,
        "pre_close":  11.27,
        "change":  -0.15,
        "pct_chg":  -1.331,
        "vol":  757757.33,
        "amount":  845283.641
    },
    {
        "ts_code":  "000001.SZ",
        "trade_date":  "20260407",
        "open":  11.12,
        "high":  11.14,
        "low":  10.97,
        "close":  11.03,
        "pre_close":  11.12,
        "change":  -0.09,
        "pct_chg":  -0.8094,
        "vol":  607955.21,
        "amount":  671322.755
    },
    {
        "ts_code":  "000001.SZ",
        "trade_date":  "20260408",
        "open":  11.11,
        "high":  11.22,
        "low":  11.05,
        "close":  11.22,
        "pre_close":  11.03,
        "change":  0.19,
        "pct_chg":  1.7226,
        "vol":  812975.89,
        "amount":  906308.305
    },
    {
        "ts_code":  "000001.SZ",
        "trade_date":  "20260409",
        "open":  11.17,
        "high":  11.22,
        "low":  11.06,
        "close":  11.1,
        "pre_close":  11.22,
        "change":  -0.12,
        "pct_chg":  -1.0695,
        "vol":  602364.93,
        "amount":  669239.285
    },
    {
        "ts_code":  "000001.SZ",
        "trade_date":  "20260410",
        "open":  11.1,
        "high":  11.13,
        "low":  11.07,
        "close":  11.09,
        "pre_close":  11.1,
        "change":  -0.01,
        "pct_chg":  -0.0901,
        "vol":  481046.93,
        "amount":  534088.991
    },
    {
        "ts_code":  "000001.SZ",
        "trade_date":  "20260413",
        "open":  11.05,
        "high":  11.09,
        "low":  11.03,
        "close":  11.07,
        "pre_close":  11.09,
        "change":  -0.02,
        "pct_chg":  -0.1803,
        "vol":  406104.13,
        "amount":  449056.814
    },
    {
        "ts_code":  "000001.SZ",
        "trade_date":  "20260414",
        "open":  11.07,
        "high":  11.17,
        "low":  11.07,
        "close":  11.17,
        "pre_close":  11.07,
        "change":  0.1,
        "pct_chg":  0.9033,
        "vol":  496151.09,
        "amount":  551741.633
    },
    {
        "ts_code":  "000001.SZ",
        "trade_date":  "20260415",
        "open":  11.16,
        "high":  11.22,
        "low":  11.15,
        "close":  11.21,
        "pre_close":  11.17,
        "change":  0.04,
        "pct_chg":  0.3581,
        "vol":  503937.93,
        "amount":  564031.568
    },
    {
        "ts_code":  "000001.SZ",
        "trade_date":  "20260416",
        "open":  11.2,
        "high":  11.23,
        "low":  11.07,
        "close":  11.09,
        "pre_close":  11.21,
        "change":  -0.12,
        "pct_chg":  -1.0705,
        "vol":  680914.6,
        "amount":  758006.903
    },
    {
        "ts_code":  "000001.SZ",
        "trade_date":  "20260417",
        "open":  11.09,
        "high":  11.11,
        "low":  10.99,
        "close":  11.01,
        "pre_close":  11.09,
        "change":  -0.08,
        "pct_chg":  -0.7214,
        "vol":  722530.42,
        "amount":  797678.406
    },
    {
        "ts_code":  "000001.SZ",
        "trade_date":  "20260420",
        "open":  11.01,
        "high":  11.07,
        "low":  10.96,
        "close":  11.06,
        "pre_close":  11.01,
        "change":  0.05,
        "pct_chg":  0.4541,
        "vol":  630033.66,
        "amount":  695097.194
    },
    {
        "ts_code":  "000001.SZ",
        "trade_date":  "20260421",
        "open":  11.04,
        "high":  11.16,
        "low":  11.03,
        "close":  11.08,
        "pre_close":  11.06,
        "change":  0.02,
        "pct_chg":  0.1808,
        "vol":  806946.34,
        "amount":  896659.539
    },
    {
        "ts_code":  "000001.SZ",
        "trade_date":  "20260422",
        "open":  11.08,
        "high":  11.09,
        "low":  10.95,
        "close":  10.98,
        "pre_close":  11.08,
        "change":  -0.1,
        "pct_chg":  -0.9025,
        "vol":  839053.99,
        "amount":  923203.009
    },
    {
        "ts_code":  "000001.SZ",
        "trade_date":  "20260423",
        "open":  10.98,
        "high":  11.03,
        "low":  10.93,
        "close":  11.0,
        "pre_close":  10.98,
        "change":  0.02,
        "pct_chg":  0.1821,
        "vol":  648066.61,
        "amount":  711757.543
    },
    {
        "ts_code":  "000001.SZ",
        "trade_date":  "20260424",
        "open":  10.98,
        "high":  11.03,
        "low":  10.92,
        "close":  11.0,
        "pre_close":  11.0,
        "change":  0.0,
        "pct_chg":  0.0,
        "vol":  582710.12,
        "amount":  639781.173
    },
    {
        "ts_code":  "000001.SZ",
        "trade_date":  "20260427",
        "open":  11.33,
        "high":  11.57,
        "low":  11.29,
        "close":  11.38,
        "pre_close":  11.0,
        "change":  0.38,
        "pct_chg":  3.4545,
        "vol":  3401275.67,
        "amount":  3891707.615
    },
    {
        "ts_code":  "000001.SZ",
        "trade_date":  "20260428",
        "open":  11.36,
        "high":  11.46,
        "low":  11.32,
        "close":  11.46,
        "pre_close":  11.38,
        "change":  0.08,
        "pct_chg":  0.703,
        "vol":  1674258.83,
        "amount":  1908333.959
    },
    {
        "ts_code":  "000001.SZ",
        "trade_date":  "20260429",
        "open":  11.43,
        "high":  11.54,
        "low":  11.39,
        "close":  11.52,
        "pre_close":  11.46,
        "change":  0.06,
        "pct_chg":  0.5236,
        "vol":  1378423.44,
        "amount":  1583294.869
    },
    {
        "ts_code":  "000001.SZ",
        "trade_date":  "20260430",
        "open":  11.5,
        "high":  11.6,
        "low":  11.46,
        "close":  11.49,
        "pre_close":  11.52,
        "change":  -0.03,
        "pct_chg":  -0.2604,
        "vol":  1139241.62,
        "amount":  1312827.776
    },
    {
        "ts_code":  "000001.SZ",
        "trade_date":  "20260506",
        "open":  11.5,
        "high":  11.5,
        "low":  11.3,
        "close":  11.36,
        "pre_close":  11.49,
        "change":  -0.13,
        "pct_chg":  -1.1314,
        "vol":  1216387.55,
        "amount":  1380730.921
    },
    {
        "ts_code":  "000001.SZ",
        "trade_date":  "20260507",
        "open":  11.37,
        "high":  11.39,
        "low":  11.3,
        "close":  11.37,
        "pre_close":  11.36,
        "change":  0.01,
        "pct_chg":  0.088,
        "vol":  936958.06,
        "amount":  1062755.239
    },
    {
        "ts_code":  "000001.SZ",
        "trade_date":  "20260508",
        "open":  11.34,
        "high":  11.42,
        "low":  11.3,
        "close":  11.3,
        "pre_close":  11.37,
        "change":  -0.07,
        "pct_chg":  -0.6157,
        "vol":  798819.86,
        "amount":  905737.835
    },
    {
        "ts_code":  "000001.SZ",
        "trade_date":  "20260511",
        "open":  11.29,
        "high":  11.31,
        "low":  11.16,
        "close":  11.28,
        "pre_close":  11.3,
        "change":  -0.02,
        "pct_chg":  -0.177,
        "vol":  931865.21,
        "amount":  1047435.369
    },
    {
        "ts_code":  "000001.SZ",
        "trade_date":  "20260512",
        "open":  11.28,
        "high":  11.36,
        "low":  11.21,
        "close":  11.25,
        "pre_close":  11.28,
        "change":  -0.03,
        "pct_chg":  -0.266,
        "vol":  1029038.42,
        "amount":  1158241.866
    },
    {
        "ts_code":  "000001.SZ",
        "trade_date":  "20260513",
        "open":  11.25,
        "high":  11.28,
        "low":  11.11,
        "close":  11.14,
        "pre_close":  11.25,
        "change":  -0.11,
        "pct_chg":  -0.9778,
        "vol":  1017973.92,
        "amount":  1136724.107
    },
    {
        "ts_code":  "000001.SZ",
        "trade_date":  "20260514",
        "open":  11.14,
        "high":  11.15,
        "low":  11.05,
        "close":  11.05,
        "pre_close":  11.14,
        "change":  -0.09,
        "pct_chg":  -0.8079,
        "vol":  794368.41,
        "amount":  881960.631
    },
    {
        "ts_code":  "000001.SZ",
        "trade_date":  "20260515",
        "open":  11.05,
        "high":  11.11,
        "low":  10.96,
        "close":  10.99,
        "pre_close":  11.05,
        "change":  -0.06,
        "pct_chg":  -0.543,
        "vol":  974741.76,
        "amount":  1074648.533
    },
    {
        "ts_code":  "000001.SZ",
        "trade_date":  "20260518",
        "open":  10.96,
        "high":  10.97,
        "low":  10.82,
        "close":  10.86,
        "pre_close":  10.99,
        "change":  -0.13,
        "pct_chg":  -1.1829,
        "vol":  856381.57,
        "amount":  931697.164
    },
    {
        "ts_code":  "000001.SZ",
        "trade_date":  "20260519",
        "open":  10.83,
        "high":  10.92,
        "low":  10.83,
        "close":  10.86,
        "pre_close":  10.86,
        "change":  0.0,
        "pct_chg":  0.0,
        "vol":  793529.13,
        "amount":  862561.883
    },
    {
        "ts_code":  "000001.SZ",
        "trade_date":  "20260520",
        "open":  10.86,
        "high":  10.88,
        "low":  10.76,
        "close":  10.77,
        "pre_close":  10.86,
        "change":  -0.09,
        "pct_chg":  -0.8287,
        "vol":  747632.14,
        "amount":  808079.589
    },
    {
        "ts_code":  "000001.SZ",
        "trade_date":  "20260521",
        "open":  10.78,
        "high":  10.8,
        "low":  10.69,
        "close":  10.7,
        "pre_close":  10.77,
        "change":  -0.07,
        "pct_chg":  -0.65,
        "vol":  1110211.08,
        "amount":  1194144.112
    },
    {
        "ts_code":  "000001.SZ",
        "trade_date":  "20260522",
        "open":  10.7,
        "high":  10.73,
        "low":  10.65,
        "close":  10.68,
        "pre_close":  10.7,
        "change":  -0.02,
        "pct_chg":  -0.1869,
        "vol":  954132.73,
        "amount":  1020057.083
    },
    {
        "ts_code":  "000001.SZ",
        "trade_date":  "20260525",
        "open":  10.68,
        "high":  10.76,
        "low":  10.64,
        "close":  10.68,
        "pre_close":  10.68,
        "change":  0.0,
        "pct_chg":  0.0,
        "vol":  663102.95,
        "amount":  709614.128
    },
    {
        "ts_code":  "000001.SZ",
        "trade_date":  "20260526",
        "open":  10.71,
        "high":  10.83,
        "low":  10.66,
        "close":  10.79,
        "pre_close":  10.68,
        "change":  0.11,
        "pct_chg":  1.03,
        "vol":  837346.9,
        "amount":  900879.538
    },
    {
        "ts_code":  "000001.SZ",
        "trade_date":  "20260527",
        "open":  10.76,
        "high":  10.85,
        "low":  10.72,
        "close":  10.76,
        "pre_close":  10.79,
        "change":  -0.03,
        "pct_chg":  -0.278,
        "vol":  839727.18,
        "amount":  905710.898
    },
    {
        "ts_code":  "000001.SZ",
        "trade_date":  "20260528",
        "open":  10.76,
        "high":  10.79,
        "low":  10.63,
        "close":  10.66,
        "pre_close":  10.76,
        "change":  -0.1,
        "pct_chg":  -0.9294,
        "vol":  900711.07,
        "amount":  963695.781
    },
    {
        "ts_code":  "000001.SZ",
        "trade_date":  "20260529",
        "open":  10.65,
        "high":  10.93,
        "low":  10.62,
        "close":  10.93,
        "pre_close":  10.66,
        "change":  0.27,
        "pct_chg":  2.5328,
        "vol":  1399367.8,
        "amount":  1515692.068
    },
    {
        "ts_code":  "000001.SZ",
        "trade_date":  "20260601",
        "open":  10.9,
        "high":  10.99,
        "low":  10.81,
        "close":  10.99,
        "pre_close":  10.93,
        "change":  0.06,
        "pct_chg":  0.5489,
        "vol":  954595.69,
        "amount":  1042306.456
    },
    {
        "ts_code":  "000001.SZ",
        "trade_date":  "20260602",
        "open":  10.98,
        "high":  11.1,
        "low":  10.94,
        "close":  11.08,
        "pre_close":  10.99,
        "change":  0.09,
        "pct_chg":  0.8189,
        "vol":  885428.42,
        "amount":  978159.337
    },
    {
        "ts_code":  "000001.SZ",
        "trade_date":  "20260603",
        "open":  11.03,
        "high":  11.06,
        "low":  10.92,
        "close":  10.99,
        "pre_close":  11.08,
        "change":  -0.09,
        "pct_chg":  -0.8123,
        "vol":  825271.72,
        "amount":  906870.268
    },
    {
        "ts_code":  "000001.SZ",
        "trade_date":  "20260604",
        "open":  10.91,
        "high":  10.97,
        "low":  10.77,
        "close":  10.82,
        "pre_close":  10.99,
        "change":  -0.17,
        "pct_chg":  -1.5469,
        "vol":  869270.83,
        "amount":  943329.311
    },
    {
        "ts_code":  "000001.SZ",
        "trade_date":  "20260605",
        "open":  10.83,
        "high":  11.03,
        "low":  10.83,
        "close":  10.98,
        "pre_close":  10.82,
        "change":  0.16,
        "pct_chg":  1.4787,
        "vol":  1003503.34,
        "amount":  1102446.143
    },
    {
        "ts_code":  "000001.SZ",
        "trade_date":  "20260608",
        "open":  10.97,
        "high":  11.1,
        "low":  10.96,
        "close":  11.03,
        "pre_close":  10.98,
        "change":  0.05,
        "pct_chg":  0.4554,
        "vol":  1090926.46,
        "amount":  1203946.343
    },
    {
        "ts_code":  "000001.SZ",
        "trade_date":  "20260609",
        "open":  11.01,
        "high":  11.19,
        "low":  10.96,
        "close":  11.13,
        "pre_close":  11.03,
        "change":  0.1,
        "pct_chg":  0.9066,
        "vol":  1149672.34,
        "amount":  1277122.41579
    },
    {
        "ts_code":  "000001.SZ",
        "trade_date":  "20260610",
        "open":  11.07,
        "high":  11.35,
        "low":  11.07,
        "close":  11.32,
        "pre_close":  11.13,
        "change":  0.19,
        "pct_chg":  1.7071,
        "vol":  1543176.39,
        "amount":  1738056.71203
    },
    {
        "ts_code":  "000001.SZ",
        "trade_date":  "20260611",
        "open":  11.32,
        "high":  11.39,
        "low":  11.25,
        "close":  11.3,
        "pre_close":  11.32,
        "change":  -0.02,
        "pct_chg":  -0.1767,
        "vol":  1156222.22,
        "amount":  1308133.97213
    },
    {
        "ts_code":  "000001.SZ",
        "trade_date":  "20260612",
        "open":  11.0,
        "high":  11.25,
        "low":  10.88,
        "close":  11.24,
        "pre_close":  10.94,
        "change":  0.3,
        "pct_chg":  2.7422,
        "vol":  2032355.46,
        "amount":  2263042.93057
    },
    {
        "ts_code":  "000001.SZ",
        "trade_date":  "20260615",
        "open":  11.21,
        "high":  11.21,
        "low":  10.98,
        "close":  11.06,
        "pre_close":  11.24,
        "change":  -0.18,
        "pct_chg":  -1.6014,
        "vol":  1541304.95,
        "amount":  1711561.28657
    },
    {
        "ts_code":  "000001.SZ",
        "trade_date":  "20260616",
        "open":  11.05,
        "high":  11.12,
        "low":  10.91,
        "close":  10.94,
        "pre_close":  11.06,
        "change":  -0.12,
        "pct_chg":  -1.085,
        "vol":  942708.04,
        "amount":  1034554.24938
    },
    {
        "ts_code":  "000001.SZ",
        "trade_date":  "20260617",
        "open":  10.97,
        "high":  10.99,
        "low":  10.75,
        "close":  10.78,
        "pre_close":  10.94,
        "change":  -0.16,
        "pct_chg":  -1.4625,
        "vol":  965828.03,
        "amount":  1046564.89554
    },
    {
        "ts_code":  "000001.SZ",
        "trade_date":  "20260618",
        "open":  10.74,
        "high":  10.77,
        "low":  10.52,
        "close":  10.52,
        "pre_close":  10.78,
        "change":  -0.26,
        "pct_chg":  -2.4119,
        "vol":  1426893.16,
        "amount":  1511009.56495
    },
    {
        "ts_code":  "000001.SZ",
        "trade_date":  "20260622",
        "open":  10.52,
        "high":  10.67,
        "low":  10.42,
        "close":  10.65,
        "pre_close":  10.52,
        "change":  0.13,
        "pct_chg":  1.2357,
        "vol":  1265316.72,
        "amount":  1334768.05278
    },
    {
        "ts_code":  "000001.SZ",
        "trade_date":  "20260623",
        "open":  10.65,
        "high":  10.91,
        "low":  10.63,
        "close":  10.71,
        "pre_close":  10.65,
        "change":  0.06,
        "pct_chg":  0.5634,
        "vol":  1190604.07,
        "amount":  1285360.40038
    },
    {
        "ts_code":  "000001.SZ",
        "trade_date":  "20260624",
        "open":  10.68,
        "high":  10.78,
        "low":  10.51,
        "close":  10.51,
        "pre_close":  10.71,
        "change":  -0.2,
        "pct_chg":  -1.8674,
        "vol":  1125841.14,
        "amount":  1193370.30356
    },
    {
        "ts_code":  "000001.SZ",
        "trade_date":  "20260625",
        "open":  10.47,
        "high":  10.59,
        "low":  10.41,
        "close":  10.42,
        "pre_close":  10.51,
        "change":  -0.09,
        "pct_chg":  -0.8563,
        "vol":  1083999.05,
        "amount":  1136742.12647
    },
    {
        "ts_code":  "000001.SZ",
        "trade_date":  "20260626",
        "open":  10.42,
        "high":  10.47,
        "low":  10.19,
        "close":  10.23,
        "pre_close":  10.42,
        "change":  -0.19,
        "pct_chg":  -1.8234,
        "vol":  1236481.64,
        "amount":  1270902.94786
    }
]
